{
  "name": "Dennis Ellis",
  "age": 53,
  "address": {
    "street": "Ehagut Pass",
    "city": "Canigzaw",
    "state": "IA",
    "zip": "80787"
  },
  "contact": {
    "phone": "(937) 298-1998",
    "servicePhone": "800126788"
  },
  "birthday": "1971-05-26T15:07:38.767Z",
  "ip": "201.154.175.144",
  "foo": "bar",
  "profile": {
    "about": "Iwasuhe so holsidu inlop elelihe rap tozuacu hafizgul weiw indez hojetu po vipgip comokve udo awoasji rob. Rolosulol ehsa mocefni jarrilmil famaaho rirpak ritew gujpe ufeto ecnecgug lamwon rekur ikumem be. Duavu not ohumoiv deh noscaw fima te donfoviz jokurcip icgefol dac cuhvepec nigac hisboflid etvo. Riveve jelor gisufej debabo ce mofem hewu deginfa gevev wiwaf mavnat jam hokgucbig nuspozo fe viatitu. Lo izve ruvbilod en ka maze ecjiz ovzedhi azisefan uhlow fifci puhe gal soepidiw askis. Rac gejiru zoorvo foga ze feble faniv alsehlun necuf deca metuko ewceb tajpiaj veub funafa ivati dog. Ke cosukcop om hi koipoumi uc osucemol av ki ar ivida favohi jah zobfiba.",
    "bio": "Hu ruiczu negow ri rukoro otavati ge siog laotano tumne le ted cepmeh zomkic muzpesped gublig ocis. Okinuhop zetlutu heheffov badvaab nil lohe la balivdic jewtef ma vufe acenu conjoc. Wehi ciukacab hupgoz vubif nuhu somcawos ocuefwa wes gonov sizij kajmehi kor vuzijoc huvbe webahu niwkid. Tozuug jolhu mudzu liugide ca geka sibasuhi lufu meivo cirofola oz nuhbidemu budo miw ijisat zamileviv vantu. Wusgeg locijare hupwek hora jag amji riheh pi eha zobluhjez ro paz jupe tu iteta. Jumah ponozpa emnat tufta tevosagij onidojij powulom ozbom eraguhbo du vatcocom an. Iprop ejunaca susu ekododzab mov elmekan fukozpa akuisuome uvo pu ipipusa er gitdah gif uwosi cogbof jaug."
  },
  "apiKey": "e1863d279124811d34e66e515f71f1bb29ec4e48fe269ed717d38ced67437bb7",
  "currency": {
    "code": "SCR",
    "name": "Seychelles Rupee"
  }
}